[
  {
    "id": "560757807",
    "title": "อุบัติเหตุ รถบรรทุกพลิกตะแคง มอเตอร์เวย์ สาย 9 จุดเกิดเหตุช่วงเชิงทางลงต่างระดับบางปะอิน ฝั่งมุ่งหน้าไป จังหวัดสระบุรี กีดขวางช่องทางขวา",
    "url": "https://www.js100.com/en/site/traffic",
    "image": null,
    "category": "อุบัติเหตุ",
    "categories": [
      "อุบัติเหตุ"
    ],
    "timestamp": "2026-07-16T17:55:00+07:00",
    "timestamp_raw": "15  กรกฎาคม 2569,   17:55น.",
    "source": "จส.100"
  },
  {
    "id": "288309062",
    "title": "อุบัติเหตุ รถเก๋ง 2 คัน ชนกัน ถนนจรัญสนิทวงศ์ ขาเข้า จากแยกพาณิชย์ธนฯ มุ่งหน้าแยกท่าพระ จุดเกิดเหตุปากซอยจรัญ 20/1 กีดขวางช่องทางซ้าย",
    "url": "https://www.js100.com/en/site/traffic",
    "image": null,
    "category": "อุบัติเหตุ",
    "categories": [
      "อุบัติเหตุ"
    ],
    "timestamp": "2026-07-16T17:54:00+07:00",
    "timestamp_raw": "15  กรกฎาคม 2569,   17:54น.",
    "source": "จส.100"
  },
  {
    "id": "867367138",
    "title": "อุบัติเหตุ ถนนราชพฤกษ์ ขาออก จากต่างระดับบางรักน้อย มุ่งหน้าต่างระดับชัยพฤกษ์ จุดเกิดเหตุหน้าสัมมากร เพลส ราชพฤกษ์ กีดขวางช่องทางกลาง",
    "url": "https://www.js100.com/en/site/traffic",
    "image": null,
    "category": "อุบัติเหตุ",
    "categories": [
      "อุบัติเหตุ"
    ],
    "timestamp": "2026-07-16T17:53:00+07:00",
    "timestamp_raw": "15  กรกฎาคม 2569,   17:53น.",
    "source": "จส.100"
  },
  {
    "id": "122286357",
    "title": "อุบัติเหตุ รถเก๋งกับจักรยานยนต์ชนกัน ถนน340 ขาเข้า จุดเกิดเหตุช่วงกลางแยกนพวงศ์ บาดเจ็บ 2 คน กีดขวางช่องทางกลาง",
    "url": "https://www.js100.com/en/site/traffic",
    "image": null,
    "category": "อุบัติเหตุ",
    "categories": [
      "อุบัติเหตุ"
    ],
    "timestamp": "2026-07-16T17:51:00+07:00",
    "timestamp_raw": "15  กรกฎาคม 2569,   17:51น.",
    "source": "จส.100"
  },
  {
    "id": "365591018",
    "title": "อุบัติเหตุ รถเก๋งชนกัน 2 คัน โทลล์เวย์ ขาเข้า จากทางขึ้นโรงกษาปณ์ มุ่งหน้าทางขึ้นอนุสรณ์สถานฯ จุดเกิดเหตุเหนือห้างฟิวเจอร์ กีดขวางช่องทางซ้าย",
    "url": "https://www.js100.com/en/site/traffic",
    "image": null,
    "category": "อุบัติเหตุ",
    "categories": [
      "อุบัติเหตุ"
    ],
    "timestamp": "2026-07-16T17:50:00+07:00",
    "timestamp_raw": "15  กรกฎาคม 2569,   17:50น.",
    "source": "จส.100"
  },
  {
    "id": "579941241",
    "title": "อุบัติเหตุ รถปิคอัพ 2 คัน ชนกัน ทางพิเศษบางพลีสุขสวัสดิ์ จากด่านปากน้ำ มุ่งหน้าด่านบางเมือง จุดเกิดเหตุช่วงกิโลเมตรที่ 12+200 ฝั่ง B กีดขวางช่องทางซ้าย",
    "url": "https://www.js100.com/en/site/traffic",
    "image": null,
    "category": "อุบัติเหตุ",
    "categories": [
      "อุบัติเหตุ"
    ],
    "timestamp": "2026-07-16T16:49:00+07:00",
    "timestamp_raw": "15  กรกฎาคม 2569,   16:49น.",
    "source": "จส.100"
  },
  {
    "id": "810774781",
    "title": "อุบัติเหตุ รถพ่วงเสียหลักพุ่งเข้าเกาะกลาง มีรถได้รับความเสียหายอีกหลายคัน ถนนลำลูกกา ขาเข้า จากคลอง4(สายไหม-วัชรพล) มุ่งหน้าคลอง2(ทางลัดเสมาฟ้าคราม) จุดเกิดเหตุ ตรงข้ามวัดโพสพผลเจริญ",
    "url": "https://www.js100.com/en/site/traffic",
    "image": null,
    "category": "อุบัติเหตุ",
    "categories": [
      "อุบัติเหตุ"
    ],
    "timestamp": "2026-07-16T16:36:00+07:00",
    "timestamp_raw": "15  กรกฎาคม 2569,   16:36น.",
    "source": "จส.100"
  },
  {
    "id": "987441509",
    "title": "รถเทรลเลอร์จอดเสีย ถนนกาญจนาภิเษก ขาออก จากต่างระดับฉิมพลี มุ่งหน้า ซ.วัดศรีประวัติ จุดเกิดเหตุ เชิงทางลงต่างระดับฉิมพลี กีดขวางช่องทางซ้ายของทางหลัก",
    "url": "https://www.js100.com/en/site/traffic",
    "image": null,
    "category": "รายงานจราจร",
    "categories": [
      "รายงานจราจร"
    ],
    "timestamp": "2026-07-16T16:34:00+07:00",
    "timestamp_raw": "15  กรกฎาคม 2569,   16:34น.",
    "source": "จส.100"
  },
  {
    "id": "742227953",
    "title": "รถปิคอัพจอดเสีย ทางด่วน1 จากโค้งวัดสะพาน จุดเกิดเหตุ ก่อนถึงทางลงท่าเรือ 300 ม. กีดขวางช่องทางซ้าย",
    "url": "https://www.js100.com/en/site/traffic",
    "image": null,
    "category": "รายงานจราจร",
    "categories": [
      "รายงานจราจร"
    ],
    "timestamp": "2026-07-16T16:17:00+07:00",
    "timestamp_raw": "15  กรกฎาคม 2569,   16:17น.",
    "source": "จส.100"
  },
  {
    "id": "401463481",
    "title": "รถ 6 ล้อ ไปรษณีย์จอดเสีย ถนนราชพฤกษ์ ขาออก จากแยกบางขุนกอง มุ่งหน้าแยกบางกรวยไทรน้อย จุดเกิดเหตุ ภายในอุโมงค์บางขุนกอง กีดขวางช่องทางซ้าย",
    "url": "https://www.js100.com/en/site/traffic",
    "image": null,
    "category": "รายงานจราจร",
    "categories": [
      "รายงานจราจร"
    ],
    "timestamp": "2026-07-16T16:16:00+07:00",
    "timestamp_raw": "15  กรกฎาคม 2569,   16:16น.",
    "source": "จส.100"
  },
  {
    "id": "471163449",
    "title": "อุบัติเหตุ รถเมล์กับรถปิคอัพชนกัน ถนนวิภาวดีรังสิต ขาออก จากแยกฐานทัพอากาศ มุ่งหน้าอนุสรณ์สถาน จุดเกิดเหตุ บนสะพานกลับรถฐานทัพอากาศ ( ขาออก-ขาเข้า) กีดขวางช่องทางซ้าย",
    "url": "https://www.js100.com/en/site/traffic",
    "image": null,
    "category": "อุบัติเหตุ",
    "categories": [
      "อุบัติเหตุ"
    ],
    "timestamp": "2026-07-16T15:51:00+07:00",
    "timestamp_raw": "15  กรกฎาคม 2569,   15:51น.",
    "source": "จส.100"
  },
  {
    "id": "406755285",
    "title": "รถเก๋งจอดเสีย ทางด่วนรามอินทราอาจณรงค์ จากทางลงด่านประชาอุทิศ มุ่งหน้าทางขึ้นด่านโยธินพัฒนา จุดเกิดเหตุ ก่อนถึงทางลง ถ.เกษตรนวมินทร์ เล็กน้อย กีดขวางช่องทางซ้าย",
    "url": "https://www.js100.com/en/site/traffic",
    "image": null,
    "category": "รายงานจราจร",
    "categories": [
      "รายงานจราจร"
    ],
    "timestamp": "2026-07-16T15:48:00+07:00",
    "timestamp_raw": "15  กรกฎาคม 2569,   15:48น.",
    "source": "จส.100"
  },
  {
    "id": "19726855",
    "title": "เพลิงไหม้บ้านเรือนประชาชน ซอยสุขาภิบาล 2 ซอย 11 เขตประเวศ เจ้าหน้าที่สถานีดับเพลิงและกู้ภัยประเวศ กำลังไปที่เกิดเหตุ",
    "url": "https://www.js100.com/en/site/traffic",
    "image": null,
    "category": "รายงานจราจร",
    "categories": [
      "รายงานจราจร"
    ],
    "timestamp": "2026-07-16T15:27:00+07:00",
    "timestamp_raw": "15  กรกฎาคม 2569,   15:27น.",
    "source": "จส.100"
  },
  {
    "id": "451420119",
    "title": "อุบัติเหตุ รถเก๋งกับรถจักรยานยนต์ชนกัน ถนนบางกรวย-ไทรน้อย จากแยกถ.รัตนาธิเบศร์ มุ่งหน้าตลาดบางบัวทอง จุดเกิดเหตุ หน้าปั๊ม PT ก่อนถึงตลาดบางบัวทอง 2 กม. กีดขวางช่องทางซ้าย",
    "url": "https://www.js100.com/en/site/traffic",
    "image": null,
    "category": "อุบัติเหตุ",
    "categories": [
      "อุบัติเหตุ"
    ],
    "timestamp": "2026-07-16T15:12:00+07:00",
    "timestamp_raw": "15  กรกฎาคม 2569,   15:12น.",
    "source": "จส.100"
  },
  {
    "id": "29524012",
    "title": "อุบัติเหตุ รถปิคอัพไม่ทราบคู่กรณี ถนนกาญจนาภิเษก ขาออก จากต่างระดับบางโคลัด มุ่งหน้าสะพานข้ามคลองภาษีเจริญ จุดเกิดเหตุ เลยสะพานข้ามคลองบางโคลัด ประมาณ 100 ม. กีดขวางช่องทางขวาของทางขนาน และ รถปิคอัพ 2 คัน ชนกัน กีดขวางช่องทางขวาของทางหลัก",
    "url": "https://www.js100.com/en/site/traffic",
    "image": null,
    "category": "อุบัติเหตุ",
    "categories": [
      "อุบัติเหตุ"
    ],
    "timestamp": "2026-07-16T15:00:00+07:00",
    "timestamp_raw": "15  กรกฎาคม 2569,   15:00น.",
    "source": "จส.100"
  },
  {
    "id": "704876461",
    "title": "มีเจ้าหน้าที่ทำงาน ถนนราชพฤกษ์ ขาออก จากต่างระดับชัยพฤกษ์ มุ่งหน้าต่างระดับ 345 ช่วงใต้ต่างระดับชัยพฤกษ์ ในช่องทางซ้ายของช่องทางหลัก",
    "url": "https://www.js100.com/en/site/traffic",
    "image": null,
    "category": "รายงานจราจร",
    "categories": [
      "รายงานจราจร"
    ],
    "timestamp": "2026-07-16T14:41:00+07:00",
    "timestamp_raw": "15  กรกฎาคม 2569,   14:41น.",
    "source": "จส.100"
  },
  {
    "id": "746585865",
    "title": "ป้ายสังกะสีขนาดใหญ่ตกหล่น มอเตอร์เวย์ สาย 7 ขาเข้า จากด่านเก็บเงินบางปะกง มุ่งหน้าด่านเก็บเงินบางบ่อ จุดเกิดเหตุ กม.42+300 แล้วเศษชิ้นส่วนกระจายเต็มพื้นถนน กีดขวางช่องทางที่ 2-3 จากซ้าย ผู้ใช้ทางโปรดระมัดระวัง",
    "url": "https://www.js100.com/en/site/traffic",
    "image": null,
    "category": "รายงานจราจร",
    "categories": [
      "รายงานจราจร"
    ],
    "timestamp": "2026-07-16T14:07:00+07:00",
    "timestamp_raw": "15  กรกฎาคม 2569,   14:07น.",
    "source": "จส.100"
  },
  {
    "id": "75108981",
    "title": "มีเจ้าหน้าที่ทำงานติดตั้งการ์ดเรล ถนนราชพฤกษ์ ขาเข้า จากแยกบางกรวยไทรน้อย ช่วงก่อนถึงทางลงอุโมงค์บางขุนกอง เล็กน้อย ในช่องทางซ้าย",
    "url": "https://www.js100.com/en/site/traffic",
    "image": null,
    "category": "รายงานจราจร",
    "categories": [
      "รายงานจราจร"
    ],
    "timestamp": "2026-07-16T14:06:00+07:00",
    "timestamp_raw": "15  กรกฎาคม 2569,   14:06น.",
    "source": "จส.100"
  },
  {
    "id": "897564070",
    "title": "รัฐบาลขอเชิญชวนหน่วยงานภาครัฐ ภาคเอกชน และประชาชน ร่วมกิจกรรมเฉลิมพระเกียรติ เนื่องในโอกาสวันเฉลิมพระชนมพรรษา พระบาทสมเด็จพระเจ้าอยู่หัว 28 กรกฎาคม 2569",
    "url": "https://www.js100.com/en/site/traffic",
    "image": null,
    "category": "รายงานจราจร",
    "categories": [
      "รายงานจราจร"
    ],
    "timestamp": "2026-07-16T13:47:00+07:00",
    "timestamp_raw": "15  กรกฎาคม 2569,   13:47น.",
    "source": "จส.100"
  },
  {
    "id": "793616424",
    "title": "พยากรณ์อากาศ ประจำวันที่ 15 กรกฎาคม 2569 กรุงเทพ และปริมณฑล มีฝนฟ้าคะนอง 60% ของพื้นที่",
    "url": "https://www.js100.com/en/site/traffic",
    "image": null,
    "category": "รายงานจราจร",
    "categories": [
      "รายงานจราจร"
    ],
    "timestamp": "2026-07-16T13:44:00+07:00",
    "timestamp_raw": "15  กรกฎาคม 2569,   13:44น.",
    "source": "จส.100"
  },
  {
    "id": "726282662",
    "title": "รถแท็กซี่จอดเสีย ถนนจรัญสนิทวงศ์ ขาเข้า ช่วงแยกบางพลัด มุ่งหน้าแยกบรมราชชนนี จุดเกิดเหตุเชิงทางขึ้นอุโมงค์บางพลัด กีดขวางช่องทางซ้าย",
    "url": "https://www.js100.com/en/site/traffic",
    "image": null,
    "category": "รายงานจราจร",
    "categories": [
      "รายงานจราจร"
    ],
    "timestamp": "2026-07-16T13:40:00+07:00",
    "timestamp_raw": "15  กรกฎาคม 2569,   13:40น.",
    "source": "จส.100"
  },
  {
    "id": "39683811",
    "title": "มีงานซ่อมถนน ถนนราชพฤกษ์ ขาออก ช่วงใต้ต่างระดับชัยพฤกษ์ ในช่องทางซ้าย",
    "url": "https://www.js100.com/en/site/traffic",
    "image": null,
    "category": "รายงานจราจร",
    "categories": [
      "รายงานจราจร"
    ],
    "timestamp": "2026-07-16T13:38:00+07:00",
    "timestamp_raw": "15  กรกฎาคม 2569,   13:38น.",
    "source": "จส.100"
  },
  {
    "id": "438309008",
    "title": "ถนนนิคมมักกะสัน ช่วงใต้ทางด่วน มุ่งหน้าถนนราชปรารภ การจราจรเคลื่อนตัวช้าสลับหยุดนิ่ง",
    "url": "https://www.js100.com/en/site/traffic",
    "image": null,
    "category": "รายงานจราจร",
    "categories": [
      "รายงานจราจร"
    ],
    "timestamp": "2026-07-16T13:35:00+07:00",
    "timestamp_raw": "15  กรกฎาคม 2569,   13:35น.",
    "source": "จส.100"
  },
  {
    "id": "652959633",
    "title": "มีงานตีเส้นจราจร ถนนวิภาวดีรังสิต ขาออก ช่วงก่อนถึง PTT Station ประมาณ 100 เมตร ในช่องทางขวาของทางขนาน",
    "url": "https://www.js100.com/en/site/traffic",
    "image": null,
    "category": "รายงานจราจร",
    "categories": [
      "รายงานจราจร"
    ],
    "timestamp": "2026-07-16T13:34:00+07:00",
    "timestamp_raw": "15  กรกฎาคม 2569,   13:34น.",
    "source": "จส.100"
  },
  {
    "id": "834927591",
    "title": "อุบัติเหตุ จักรยานยนต์ล้มไม่ทราบคู่กรณี ถนนวัฒนธรรม จุดเกิดเหตุเลยแยกเทียมร่วมมิตร เล็กน้อย มุ่งหน้าแยกผังเมือง บาดเจ็บ 1 คน กีดขวางช่องทางซ้าย",
    "url": "https://www.js100.com/en/site/traffic",
    "image": null,
    "category": "อุบัติเหตุ",
    "categories": [
      "อุบัติเหตุ"
    ],
    "timestamp": "2026-07-16T13:31:00+07:00",
    "timestamp_raw": "15  กรกฎาคม 2569,   13:31น.",
    "source": "จส.100"
  },
  {
    "id": "148662870",
    "title": "อุบัติเหตุ จักรยานยนต์กับรถเก๋งชนกัน ถนนราชพฤกษ์ ขาออก จุดเกิดเหตุกลางต่างระดับชัยพฤกษ์ กีดขวางช่องทางซ้ายของทางหลัก",
    "url": "https://www.js100.com/en/site/traffic",
    "image": null,
    "category": "อุบัติเหตุ",
    "categories": [
      "อุบัติเหตุ"
    ],
    "timestamp": "2026-07-16T13:25:00+07:00",
    "timestamp_raw": "15  กรกฎาคม 2569,   13:25น.",
    "source": "จส.100"
  },
  {
    "id": "492844796",
    "title": "อัปเดตสถานการณ์เหตุเพลิงไหม้ โรงเบียร์ ณ ลาดพร้าว ข้อมูล ณ เวลา 11.00 น. วันที่ 15 กรกฎาคม 2569 ผู้เสียชีวิต จำนวน 32 ราย ผู้ได้รับบาดเจ็บ จำนวน 73 ราย แบ่งเป็นกลุ่มอาการสีแดง 15 ราย กลุ่มอาการสีเหลือง 15 ราย และกลุ่มอาการสีเขียว 43 ราย",
    "url": "https://www.js100.com/en/site/traffic",
    "image": null,
    "category": "รายงานจราจร",
    "categories": [
      "รายงานจราจร"
    ],
    "timestamp": "2026-07-16T13:23:00+07:00",
    "timestamp_raw": "15  กรกฎาคม 2569,   13:23น.",
    "source": "จส.100"
  },
  {
    "id": "606824617",
    "title": "แจ้งปิดเบี่ยงการจราจรเพิ่มเติมบนถนนราชปรารภ บริเวณร้านวัสดุก่อสร้างง่วนเฮงหลี ถึงบริเวณซอยรางน้ำ ตั้งแต่วันที่ 15 กรกฎาคม เวลา 22.00 น. – 15 สิงหาคม 2569 เวลา 24.00 น. ตลอด 24 ชั่วโมง",
    "url": "https://www.js100.com/en/site/traffic",
    "image": null,
    "category": "ก่อสร้าง",
    "categories": [
      "ก่อสร้าง"
    ],
    "timestamp": "2026-07-16T13:18:00+07:00",
    "timestamp_raw": "15  กรกฎาคม 2569,   13:18น.",
    "source": "จส.100"
  },
  {
    "id": "140786730",
    "title": "รฟม. แจ้งปิดเบี่ยงการจราจรถนนเพชรบุรี บริเวณซอยเพชรบุรี 4 ถึงแยกอุรุพงษ์ ตั้งแต่วันที่ 17 กรกฎาคม 2569 – 31 กรกฎาคม 2569 ช่วงเวลา 22.00 น. – 05.00 น. เฉพาะเวลากลางคืน",
    "url": "https://www.js100.com/en/site/traffic",
    "image": null,
    "category": "รายงานจราจร",
    "categories": [
      "รายงานจราจร"
    ],
    "timestamp": "2026-07-16T13:15:00+07:00",
    "timestamp_raw": "15  กรกฎาคม 2569,   13:15น.",
    "source": "จส.100"
  },
  {
    "id": "759636410",
    "title": "ปิดจุดกลับรถก่อนถึงแยกบรมราชชนนี ขาเข้า เจ้าพนักงานจราจรจะทำการทดสอบความคล่องตัวของรถ ในการใช้จุดกลับรถใกล้แยกบรมราชชนนีจึงทำการปิดกั้นจุดกลับรถดังกล่าวชั่วคราว และเพื่อซ่อมแซมราวสะพานความสูงด้านบนที่ได้รับความเสียหาย เพื่อความปลอดภัยแก่ผู้ใช้รถใช้ถนน",
    "url": "https://www.js100.com/en/site/traffic",
    "image": null,
    "category": "ปกติ",
    "categories": [
      "ปกติ"
    ],
    "timestamp": "2026-07-16T13:12:00+07:00",
    "timestamp_raw": "15  กรกฎาคม 2569,   13:12น.",
    "source": "จส.100"
  },
  {
    "id": "454091582",
    "title": "วันที่ 15 กรกฎาคม 2569 เวลา 13.00 - 15.00 น. โรงเรียนวัดสิตาราม ถนนดำรงรักษ์ เขตป้อมปราบศัตรูพ่าย จะทำการซ้อมแผนดับเพลิงและซ้อมอพยพหนีไฟ",
    "url": "https://www.js100.com/en/site/traffic",
    "image": null,
    "category": "รายงานจราจร",
    "categories": [
      "รายงานจราจร"
    ],
    "timestamp": "2026-07-16T12:33:00+07:00",
    "timestamp_raw": "15  กรกฎาคม 2569,   12:33น.",
    "source": "จส.100"
  },
  {
    "id": "109881278",
    "title": "รถเมล์จอดเสีย ถนนแจ้งวัฒนะ ขาเข้า จากตรงข้ามศูนย์ราชการ แจ้งวัฒนะ มุ่งหน้าตรงข้ามมหาวิทยาลัยราชภัฏพระนคร จุดเกิดเหตุ ลงจากสะพานข้าม ถ.วิภาวดี เล็กน้อย กีดขวางช่องทางซ้าย",
    "url": "https://www.js100.com/en/site/traffic",
    "image": null,
    "category": "รายงานจราจร",
    "categories": [
      "รายงานจราจร"
    ],
    "timestamp": "2026-07-16T12:09:00+07:00",
    "timestamp_raw": "15  กรกฎาคม 2569,   12:09น.",
    "source": "จส.100"
  },
  {
    "id": "933053955",
    "title": "ถังน้ำมันตกหล่น ถนนมิตรไมตรี จากถ.วิภาวดีรังสิต มุ่งหน้าถ.ประชาสงเคราะห์ จุดเกิดเหตุ เลยแยกตัด ถ.วิภาวดีรังสิต เล็กน้อย กีดขวางช่องทางกลาง และมีคราบน้ำมันหก ผู้ใช้ทางโปรดระมัดระวัง",
    "url": "https://www.js100.com/en/site/traffic",
    "image": null,
    "category": "รายงานจราจร",
    "categories": [
      "รายงานจราจร"
    ],
    "timestamp": "2026-07-16T12:06:00+07:00",
    "timestamp_raw": "15  กรกฎาคม 2569,   12:06น.",
    "source": "จส.100"
  },
  {
    "id": "75736325",
    "title": "วันที่ 15 กรกฎาคม 2569 เวลา 13.00 - 16.00 น. วิลล่าเทวา รีสอร์ท แอนด์ โฮเทล ซอยสาทร 1 แขวงทุ่งมหาเมฆ เขตสาทร จะทำการซ้อมแผนดับเพลิงและซ้อมอพยพหนีไฟ",
    "url": "https://www.js100.com/en/site/traffic",
    "image": null,
    "category": "รายงานจราจร",
    "categories": [
      "รายงานจราจร"
    ],
    "timestamp": "2026-07-16T12:03:00+07:00",
    "timestamp_raw": "15  กรกฎาคม 2569,   12:03น.",
    "source": "จส.100"
  },
  {
    "id": "5286070",
    "title": "เพลิงไหม้กองขยะ ซอยประชาอุทิศ 99 ถนนประชาอุทิศ แขวงทุ่งครุ เขตทุ่งครุ เจ้าหน้าที่สถานีดับเพลิงและกู้ภัยทุ่งครุ กำลังไปที่เกิดเหตุ",
    "url": "https://www.js100.com/en/site/traffic",
    "image": null,
    "category": "รายงานจราจร",
    "categories": [
      "รายงานจราจร"
    ],
    "timestamp": "2026-07-16T11:27:00+07:00",
    "timestamp_raw": "15  กรกฎาคม 2569,   11:27น.",
    "source": "จส.100"
  },
  {
    "id": "642939635",
    "title": "15 ก.ค. 69 เวลา 22.00-05.00 น. กปน. หยุดจ่ายน้ำ ชั่วคราว เพื่อสำรวจท่อประธาน บริเวณคลองแสนแสบ ถนนบรรทัดทอง ส่งผลให้น้ำประปาไหลอ่อนถึงไม่ไหล",
    "url": "https://www.js100.com/en/site/traffic",
    "image": null,
    "category": "รายงานจราจร",
    "categories": [
      "รายงานจราจร"
    ],
    "timestamp": "2026-07-16T11:20:00+07:00",
    "timestamp_raw": "15  กรกฎาคม 2569,   11:20น.",
    "source": "จส.100"
  },
  {
    "id": "616117856",
    "title": "รถSUVจอดเสีย สะพานพระราม3 ขาเข้า จากทางขึ้นถนนตากสิน มุ่งหน้า ทางแยกลงถนนเจริญกรุง จุดเกิดเหตุ ที่เชิงทางขึ้นสะพานพระราม3 ขวางช่องทางกลาง",
    "url": "https://www.js100.com/en/site/traffic",
    "image": null,
    "category": "รายงานจราจร",
    "categories": [
      "รายงานจราจร"
    ],
    "timestamp": "2026-07-16T11:15:00+07:00",
    "timestamp_raw": "15  กรกฎาคม 2569,   11:15น.",
    "source": "จส.100"
  },
  {
    "id": "64420701",
    "title": "อุบัติเหตุ รถชนกัน 2 คัน ถนนบรมราชชนนี ขาออก จากพุทธมณฑลสาย2 มุ่งหน้าพุทธมณฑลสาย4 จุดเกิดเหตุ ตรงข้ามตลาดธนบุรี กีดขวางช่องทางขวาของทางหลัก",
    "url": "https://www.js100.com/en/site/traffic",
    "image": null,
    "category": "อุบัติเหตุ",
    "categories": [
      "อุบัติเหตุ"
    ],
    "timestamp": "2026-07-16T11:06:00+07:00",
    "timestamp_raw": "15  กรกฎาคม 2569,   11:06น.",
    "source": "จส.100"
  },
  {
    "id": "873672177",
    "title": "อุบัติเหตุ รถเก๋ง 2 คัน ชนกัน มอเตอร์เวย์ สาย 7 ขาเข้า จากต่างระดับทับช้าง มุ่งหน้าต่างระดับถนนศรีนครินทร์ จุดเกิดเหตุ กม.3+900 กีดขวางช่องทางขวา",
    "url": "https://www.js100.com/en/site/traffic",
    "image": null,
    "category": "อุบัติเหตุ",
    "categories": [
      "อุบัติเหตุ"
    ],
    "timestamp": "2026-07-16T10:51:00+07:00",
    "timestamp_raw": "15  กรกฎาคม 2569,   10:51น.",
    "source": "จส.100"
  },
  {
    "id": "518700117",
    "title": "มีสายไฟประดับห้อยลงมา ถนนศรีสมาน ขาออก จากศรีสมาน มุ่งหน้าใต้ทางด่วนศรีสมาน จุดเกิดเหตุ เลยโรบินสันศรีสมาน ประมาณ 500 ม. ในช่องทางซ้าย ผู้ใช้ทางโปรดระมัดระวัง",
    "url": "https://www.js100.com/en/site/traffic",
    "image": null,
    "category": "รายงานจราจร",
    "categories": [
      "รายงานจราจร"
    ],
    "timestamp": "2026-07-16T10:34:00+07:00",
    "timestamp_raw": "15  กรกฎาคม 2569,   10:34น.",
    "source": "จส.100"
  }
]